{
  "title": "Gucci vs Louis Vuitton",
  "entityA": "Gucci",
  "entityB": "Louis Vuitton",
  "category": "General",
  "slug": "gucci-vs-louis-vuitton",
  "shortAnswer": "Louis Vuitton leads in prestige and heritage, while Gucci excels in bold fashion-forward design. Both are luxury pinnacles with different strengths.",
  "keyDifferences": [
    {
      "label": "Prestige Level",
      "entityAValue": "High luxury status",
      "entityBValue": "Higher prestige overall",
      "winner": "b"
    },
    {
      "label": "Design Approach",
      "entityAValue": "Bold fashion-forward designs",
      "entityBValue": "Classic heritage styling",
      "winner": "a"
    },
    {
      "label": "Material Quality",
      "entityAValue": "Superior leather and canvas quality",
      "entityBValue": "Good quality materials",
      "winner": "a"
    },
    {
      "label": "Brand Heritage",
      "entityAValue": "Strong luxury heritage",
      "entityBValue": "Superior brand value and heritage",
      "winner": "b"
    },
    {
      "label": "Style Focus",
      "entityAValue": "Contemporary bold looks",
      "entityBValue": "Timeless classic designs",
      "winner": "tie"
    }
  ],
  "stats": [
    {
      "label": "Resale Value Retention",
      "valueA": "50-70%",
      "valueB": "70-80%+",
      "winner": "b"
    },
    {
      "label": "Practicality Rating",
      "valueA": "High",
      "valueB": "High",
      "winner": "tie"
    },
    {
      "label": "Casual Wear Suitability",
      "valueA": "Good",
      "valueB": "Good",
      "winner": "tie"
    },
    {
      "label": "Brand Recognition",
      "valueA": "Very High",
      "valueB": "Very High",
      "winner": "tie"
    },
    {
      "label": "Material Quality Score",
      "valueA": "Excellent",
      "valueB": "Very Good",
      "winner": "a"
    },
    {
      "label": "Overall Prestige Ranking",
      "valueA": "High Tier",
      "valueB": "Top Tier",
      "winner": "b"
    },
    {
      "label": "Fashion Innovation",
      "valueA": "Leading",
      "valueB": "Traditional",
      "winner": "a"
    },
    {
      "label": "Investment Value",
      "valueA": "Good",
      "valueB": "Better",
      "winner": "b"
    }
  ],
  "prosA": [
    "Bold fashion-forward designs",
    "Superior leather and canvas quality",
    "Contemporary style appeal",
    "Strong luxury brand status"
  ],
  "consA": [
    "Lower resale value retention",
    "Less prestigious than Louis Vuitton"
  ],
  "prosB": [
    "Higher overall prestige",
    "Better resale value retention (70-80%+)",
    "Superior brand heritage and value",
    "Timeless classic appeal"
  ],
  "consB": [
    "Less bold in design innovation",
    "More traditional styling approach"
  ],
  "verdict": "Louis Vuitton leads in brand value, heritage, and resale value retention. Gucci excels in bold fashion-forward design and material quality. Both represent pinnacles of luxury with distinct strengths for different preferences."
}